Workbook

Sheet Допущения
A1: ЗАЛОГОВАЯ ИНВЕСТ-ПЛАТФОРМА — КЛЮЧЕВЫЕ ДОПУЩЕНИЯ
A2: Синие ячейки — вводные (можно менять). Чёрные — формулы.
A4: Параметр | B4: Значение | C4: Ед. | D4: Обоснование
A5: ОБЪЁМ И СДЕЛКИ
A6: Объём финансирования в месяц (база) | B6: 100000000 | C6: руб/мес | D6: Базовый сценарий по ТЗ
A7: Средний размер сделки | B7: 2500000 | C7: руб | D7: Микс: недвижимость 5–7 млн, авто 1–1.5 млн, спецтехника 2–3 млн. Взвеш. ~2.5 млн
A8: Количество сделок в месяц | B8: =B6/B7 | C8: шт | D8: Объём / Средний чек
A9: Средний срок займа | B9: 12 | C9: мес | D9: Залоговые займы 6–18 мес
A11: КОМИССИИ (TAKE RATE, % от суммы займа)
A12: Комиссия с заёмщика | B12: 0.035 | C12: % от займа | D12: Повышено до 3.5% (Вариант 3)
A13: Комиссия с инвестора | B13: 0.015 | C13: % от займа | D13: Сервисный сбор за подбор сделок: 1–2%
A14: Доп. услуги (юр., ускор., страх., VIP) | B14: 0.015 | C14: % от займа | D14: Допуслуги 1.5%: юр.сопровождение, ускор.проверка, страхование, VIP
A15: ИТОГО take rate | B15: =B12+B13+B14 | C15: % от займа
A17: ПЕРЕМЕННЫЕ РАСХОДЫ (% от объёма)
A18: Проверка/оценка залога | B18: 0.005 | C18: % от объёма | D18: ИИ-оценка залога автоматически; ручная аналитика ~15% сделок (стоп-факторы). ~12 тыс ₽/сделку взвеш.
A19: Резервный (гарантийный) фонд | B19: 0.005 | C19: % от объёма | D19: Provision/buyback fund 0.5% для доверия инвесторов
A20: Маркетинг / привлечение (CAC) | B20: 0.007 | C20: % от объёма | D20: 0.7% — упор на рефералов и сарафан (Вариант 3)
A21: Эквайринг / платежи | B21: 0.0002 | C21: % от объёма | D21: ~0.3% от комиссий
A22: ИТОГО переменные | B22: =B18+B19+B20+B21 | C22: % от объёма
A23: Маржа вклада (contribution margin) | B23: =B15-B22 | C23: % от объёма
A25: ПОСТОЯННЫЕ РАСХОДЫ (база, 100 млн/мес)
A26: ФОТ команды (с налогами) | B26: 1300000 | C26: руб/мес | D26: Компактная команда ~7 чел (Вариант 3): ИИ-автоматизация + стоп-факторы, юр.экспертиза, продажи
A27: Аренда и офис | B27: 200000 | C27: руб/мес
A28: IT-инфраструктура и ИИ-скоринг | B28: 700000 | C28: руб/мес | D28: ML-модели, ИИ-скоринг, OCR-оценка залога, API БКИ, compute
A29: Прочие админ. расходы | B29: 200000 | C29: руб/мес | D29: Бухгалтерия, связь, ПО
A30: ИТОГО постоянные (база) | B30: =B26+B27+B28+B29
A32: НАЛОГИ И ОЦЕНКА
A33: Налог на прибыль | B33: 0.25 | C33: % | D33: ОСНО, ставка налога на прибыль РФ с 2025 = 25%
A34: Налог на дивиденды (НДФЛ) | B34: 0.13 | C34: % | D34: НДФЛ на дивиденды собственника
A35: Дефолт по портфелю (справочно) | B35: 0.05 | C35: % | D35: 4–6% — влияет на доход инвестора, не на P&L платформы (риск у инвестора)
A36: Мультипликатор EV/EBITDA | B36: 10 | C36: x | D36: Финтех-маркетплейсы 8–12x
A37: Мультипликатор EV/Revenue | B37: 4 | C37: x | D37: Растущие финтехи 3–5x
A38: Ставка дисконтирования (WACC) | B38: 0.30 | C38: % | D38: Венчур РФ, ранняя стадия 25–35%
A39: Терминальный рост (g) | B39: 0.04 | C39: % | D39: Долгосрочный рост ~инфляция

Sheet Unit Economics
A1: UNIT ECONOMICS ОДНОЙ СДЕЛКИ
A2: Средняя сделка по базовым допущениям
A4: Показатель | B4: Значение | C4: Формула/ед. | D4: Комментарий
A5: Средний размер займа | B5: =Допущения!B7
A6: Срок займа, мес | B6: =Допущения!B9
A7: ДОХОДЫ С СДЕЛКИ
A8: Комиссия с заёмщика | B8: =B5*Допущения!B12 | D8: 3% от займа
A9: Комиссия с инвестора | B9: =B5*Допущения!B13 | D9: 1.5% от займа
A10: Доп. услуги | B10: =B5*Допущения!B14 | D10: 1% от займа
A11: Выручка с сделки | B11: =B8+B9+B10
A12: ПЕРЕМЕННЫЕ РАСХОДЫ С СДЕЛКИ
A13: Проверка/оценка залога | B13: =B5*Допущения!B18
A14: Резервный фонд | B14: =B5*Допущения!B19
A15: Маркетинг/CAC | B15: =B5*Допущения!B20
A16: Эквайринг | B16: =B5*Допущения!B21
A17: Переменные расходы с сделки | B17: =B13+B14+B15+B16
A18: Маржа вклада с сделки (₽) | B18: =B11-B17
A19: Маржа вклада, % | B19: =B18/B5 | D19: contribution margin
A20: Доходность на 1 ₽ выданного объёма | B20: =B18/B5 | D20: ключевая метрика юнита

Sheet P&L (база)
A1: P&L — БАЗОВЫЙ СЦЕНАРИЙ (100 млн ₽/мес)
A4: Статья | B4: В месяц | C4: В год | D4: Комментарий
A5: Объём финансирования | B5: =Допущения!B6 | C5: =B5*12
A6: Количество сделок | B6: =Допущения!B8 | C6: =B6*12
A7: Комиссия с заёмщика | B7: =Допущения!B6*Допущения!B12 | C7: =B7*12
A8: Комиссия с инвестора | B8: =Допущения!B6*Допущения!B13 | C8: =B8*12
A9: Доп. услуги | B9: =Допущения!B6*Допущения!B14 | C9: =B9*12
A10: ВЫРУЧКА (Revenue) | B10: =B7+B8+B9 | C10: =B10*12
A11: Проверка/оценка залога | B11: =-Допущения!B6*Допущения!B18 | C11: =B11*12
A12: Резервный фонд | B12: =-Допущения!B6*Допущения!B19 | C12: =B12*12
A13: Маркетинг/CAC | B13: =-Допущения!B6*Допущения!B20 | C13: =B13*12
A14: Эквайринг | B14: =-Допущения!B6*Допущения!B21 | C14: =B14*12
A15: Переменные расходы | B15: =SUM(B11:B14) | C15: =B15*12
A16: Маржа вклада (Gross profit) | B16: =B10+B15 | C16: =B16*12
A17: Постоянные расходы (OpEx) | B17: =-Допущения!B30 | C17: =B17*12 | D17: ФОТ, офис, IT, админ
A18: EBITDA | B18: =B16+B17 | C18: =B18*12
A19: Рентабельность по EBITDA | B19: =B18/B10 | C19: =B19*12
A20: Амортизация (D&A) | B20: =-50000 | C20: =B20*12 | D20: оборудование/ПО
A21: EBIT | B21: =B18+B20 | C21: =B21*12
A22: Налог на прибыль | B22: =-MAX(0,B21)*Допущения!B33 | C22: =B22*12 | D22: 25%, только при прибыли
A23: ЧИСТАЯ ПРИБЫЛЬ | B23: =B21+B22 | C23: =B23*12
A24: Чистая маржа | B24: =B23/B10 | C24: =B24*12
A26: При базе 100 млн/мес проект уже прибыльный (~1,75 млн ₽/мес чистыми): объём выше точки безубыточности (≈50 млн/мес).

Sheet Cash Flow
A1: ДВИЖЕНИЕ ДЕНЕЖНЫХ СРЕДСТВ (база, в месяц)
A2: Маркетплейс не выдаёт займы из своих средств — деньги инвесторов идут напрямую заёмщику. На балансе платформы только комиссии.
A4: Статья | B4: В месяц | C4: В год | D4: Комментарий
A5: Чистая прибыль | B5: ='P&L (база)'!B23 | C5: =B5*12 | D5: из P&L
A6: (+) Амортизация | B6: =-'P&L (база)'!B20 | C6: =B6*12 | D6: неденежная
A7: Операционный денежный поток (OCF) | B7: =B5+B6 | C7: =B7*12
A8: CAPEX (инвестиции) | B8: =-100000 | C8: =B8*12 | D8: оборудование, развитие платформы
A9: Свободный денежный поток (FCF) | B9: =B7+B8 | C9: =B9*12
A11: Примечание: резервный фонд (0.5%) учитывается как расход в P&L и формирует подушку на выкуп дефолтных займов.

Sheet Прогноз по объёмам
A1: ПРОГНОЗ ПО ОБЪЁМАМ СДЕЛОК (показатели в месяц, если не указано)
A3: Показатель / Объём в мес | B3: 100 млн | C3: 300 млн | D3: 500 млн | E3: 1 млрд | F3: 3 млрд | G3: 5 млрд
A4: Объём финансирования (₽) | B4: 100000000 | C4: 300000000 | D4: 500000000 | E4: 1000000000 | F4: 3000000000 | G4: 5000000000
A5: Кол-во сделок | B5: =B4/Допущения!B7 | C5: =C4/Допущения!B7 | D5: =D4/Допущения!B7 | E5: =E4/Допущения!B7 | F5: =F4/Допущения!B7 | G5: =G4/Допущения!B7
A6: Выручка (Revenue) | B6: =B4*Допущения!B15 | C6: =C4*Допущения!B15 | D6: =D4*Допущения!B15 | E6: =E4*Допущения!B15 | F6: =F4*Допущения!B15 | G6: =G4*Допущения!B15
A7: Переменные расходы | B7: =-B4*Допущения!B22 | C7: =-C4*Допущения!B22 | D7: =-D4*Допущения!B22 | E7: =-E4*Допущения!B22 | F7: =-F4*Допущения!B22 | G7: =-G4*Допущения!B22
A8: Маржа вклада | B8: =B6+B7 | C8: =C6+C7 | D8: =D6+D7 | E8: =E6+E7 | F8: =F6+F7 | G8: =G6+G7
A9: Постоянные расходы (OpEx) | B9: -2400000 | C9: -3400000 | D9: -4400000 | E9: -6500000 | F9: -12000000 | G9: -18000000
A10: EBITDA | B10: =B8+B9 | C10: =C8+C9 | D10: =D8+D9 | E10: =E8+E9 | F10: =F8+F9 | G10: =G8+G9
A11: Рентабельность EBITDA | B11: =B10/B6 | C11: =C10/C6 | D11: =D10/D6 | E11: =E10/E6 | F11: =F10/F6 | G11: =G10/G6
A12: Налог на прибыль (25%) | B12: =-MAX(0,B10)*Допущения!B33 | C12: =-MAX(0,C10)*Допущения!B33 | D12: =-MAX(0,D10)*Допущения!B33 | E12: =-MAX(0,E10)*Допущения!B33 | F12: =-MAX(0,F10)*Допущения!B33 | G12: =-MAX(0,G10)*Допущения!B33
A13: Чистая прибыль (мес) | B13: =B10+B12 | C13: =C10+C12 | D13: =D10+D12 | E13: =E10+E12 | F13: =F10+F12 | G13: =G10+G12
A14: Чистая маржа | B14: =B13/B6 | C14: =C13/C6 | D14: =D13/D6 | E14: =E13/E6 | F14: =F13/F6 | G14: =G13/G6
A15: Чистая прибыль (год) | B15: =B13*12 | C15: =C13*12 | D15: =D13*12 | E15: =E13*12 | F15: =F13*12 | G15: =G13*12
A16: EBITDA (год) | B16: =B10*12 | C16: =C10*12 | D16: =D10*12 | E16: =E10*12 | F16: =F10*12 | G16: =G10*12
A17: Выручка (год) | B17: =B6*12 | C17: =C6*12 | D17: =D6*12 | E17: =E6*12 | F17: =F6*12 | G17: =G6*12
A19: Постоянные расходы растут МЕДЛЕННО благодаря ИИ-автоматизации: ИИ обрабатывает кратно больше сделок без линейного найма. Люди добавляются в основном на стоп-факторы и сложную юр.экспертизу.

Sheet Точка безубыточности
A1: ТОЧКА БЕЗУБЫТОЧНОСТИ И ВЫХОД В ПЛЮС
A4: Показатель | B4: Значение | C4: Формула / комментарий
A5: Маржа вклада (% от объёма) | B5: =Допущения!B23 | C5: take rate − переменные
A6: Постоянные расходы (база/мес) | B6: =Допущения!B30
A7: Точка безубыточности — объём/мес | B7: =B6/B5 | C7: Постоянные / маржа вклада
A8: Точка безубыточности — сделок/мес | B8: =B7/Допущения!B7 | C8: Объём ББ / средний чек
A9: Точка безубыточности — объём/год | B9: =B7*12
A11: МИНИМАЛЬНЫЙ ОБЪЁМ ДЛЯ ВЫХОДА В ПЛЮС
A12: Минимальный объём (= точка ББ) | B12: =B7 | C12: ниже — убыток, выше — прибыль
A13: Запас прочности при объёме 300 млн | B13: =(300000000-B7)/300000000 | C13: margin of safety
A15: Чувствительность точки ББ к take rate:
A16: Take rate | B16: Точка ББ (объём/мес) | C16: Комментарий
A17: 0.04 | B17: =B6/(A17-Допущения!B22) | C17: при базовых переменных расходах
A18: 0.05 | B18: =B6/(A18-Допущения!B22) | C18: при базовых переменных расходах
A19: 0.055 | B19: =B6/(A19-Допущения!B22) | C19: при базовых переменных расходах
A20: 0.06 | B20: =B6/(A20-Допущения!B22) | C20: при базовых переменных расходах
A21: 0.07 | B21: =B6/(A21-Допущения!B22) | C21: при базовых переменных расходах

Sheet Оценка капитализации
A1: ОЦЕНКА КАПИТАЛИЗАЦИИ (3 / 5 / 10 лет)
A2: Сценарий роста: год 3 ≈ 1 млрд/мес, год 5 ≈ 3 млрд/мес, год 10 ≈ 5 млрд/мес.
A4: Показатель | B4: Год 3 | C4: Год 5 | D4: Год 10 | E4: Комментарий
A5: Объём финансирования/мес | B5: ='Прогноз по объёмам'!E4 | C5: ='Прогноз по объёмам'!F4 | D5: ='Прогноз по объёмам'!G4 | E5: из листа прогноза
A6: Выручка (год) | B6: ='Прогноз по объёмам'!E17 | C6: ='Прогноз по объёмам'!F17 | D6: ='Прогноз по объёмам'!G17
A7: EBITDA (год) | B7: ='Прогноз по объёмам'!E16 | C7: ='Прогноз по объёмам'!F16 | D7: ='Прогноз по объёмам'!G16
A8: Чистая прибыль (год) | B8: ='Прогноз по объёмам'!E15 | C8: ='Прогноз по объёмам'!F15 | D8: ='Прогноз по объёмам'!G15
A10: МЕТОДЫ ОЦЕНКИ
A11: 1) EV/EBITDA (×10) | B11: =B7*Допущения!B36 | C11: =C7*Допущения!B36 | D11: =D7*Допущения!B36
A12: 2) EV/Revenue (×4) | B12: =B6*Допущения!B37 | C12: =C6*Допущения!B37 | D12: =D6*Допущения!B37
A13: 3) DCF (приведённая стоимость) | B13: =B8*(1+Допущения!B39)/(Допущения!B38-Допущения!B39) | C13: =C8*(1+Допущения!B39)/(Допущения!B38-Допущения!B39) | D13: =D8*(1+Допущения!B39)/(Допущения!B38-Допущения!B39) | E13: FCF≈ЧП, тек. стоимость + терминал, дисконт WACC
A14: СРЕДНЯЯ ОЦЕНКА (капитализация) | B14: =AVERAGE(B11,B12,B13) | C14: =AVERAGE(C11,C12,C13) | D14: =AVERAGE(D11,D12,D13) | E14: среднее трёх методов
A16: DCF (perpetuity Гордона) даёт устойчивую оценку при высокой марже; мультипликаторы — рыночный ориентир.
A17: Все оценки — Enterprise Value без учёта долга/кэша. Для венчура применяйте дисконт за ликвидность/риск 30–50%.

Sheet Сравнение конкурентов
A1: СРАВНЕНИЕ С МИРОВЫМИ P2P/МАРКЕТПЛЕЙСАМИ
A3: Платформа | B3: Модель | C3: Сильные стороны | D3: Слабые стороны | E3: Что внедрить в России
A4: LendingClub | B4: P2P потреб. кредиты (США), позже банк | C4: Огромный масштаб, бренд, скоринг на данных, секьюритизация | D4: Ушли от чистого P2P к банку; высокие costs; регуляторное давление | E4: Сильный ИИ-скоринг и автоматизация андеррайтинга; прозрачные рейтинги заёмщиков
A5: Prosper | B5: P2P потреб. кредиты (США), пионер | C5: Первый P2P в США, отлаженный риск-менеджмент, вторичный рынок | D5: Дефолты в кризисы, зависимость от институционалов | E5: Вторичный рынок переуступки долей инвесторов для ликвидности
A6: Groundfloor | B6: Краудинвест в недвижимость под залог (США) | C6: Залог недвижимости, низкий порог входа ($10), короткие сроки | D6: Концентрация на одном классе активов, риск рынка недвижимости | E6: Залоговая модель с низким порогом + краткосрочные займы под ремонт/флиппинг
A7: EstateGuru | B7: Залоговые займы под недвижимость (Европа) | C7: Залог недвижимости 1-й очереди, трансгранично, LTV-дисциплина | D7: Рост дефолтов 2022–23, взыскание залога медленное | E7: Жёсткий LTV (≤70%), залог 1-й очереди, прозрачная статистика взысканий
A8: Mintos | B8: Маркетплейс займов от кредиторов (Европа) | C8: Агрегатор от десятков ориджинаторов, авто-инвест, buyback | D8: Риск ориджинатора (банкротства), сложность для новичка | E8: Авто-инвестирование, диверсификация, buyback-гарантия как стандарт доверия
A9: PeerBerry | B9: Маркетплейс потреб./залог займов (Европа) | C9: Простой UX, buyback, группа гарантий, высокая доходность | D9: Высокий риск групп-гарантий, мелкие займы, геориски | E9: Удобный мобильный UX + групповые гарантии для удержания инвесторов
A11: Вывод: для РФ оптимален гибрид EstateGuru (залог недвижимости, LTV-дисциплина) + Mintos/PeerBerry (buyback, авто-инвест, UX) + LendingClub (ИИ-скоринг).

Sheet Вердикт и меморандум
B1: ИНВЕСТИЦИОННЫЙ ВЕРДИКТ
B3: РЕЗЮМЕ ПРОЕКТА
B4: Маркетплейс залогового финансирования, соединяющий частных инвесторов и заёмщиков напрямую. Доход — комиссии с обеих сторон (take rate ~5.5% от объёма) + платные сервисы. Риск дефолта несёт инвестор; платформа держит резервный/buyback фонд.
B5: Средний чек 2.5 млн ₽; при 100 млн/мес — 40 сделок. Точка безубыточности ≈ 50 млн ₽/мес (~20 сделок). Модель высокомаржинальна: EBITDA-маржа растёт с 37% (100 млн) до ~60–68% на масштабе.
B6: ЖИЗНЕСПОСОБНОСТЬ МОДЕЛИ: 7 / 10
B7: Сильная юнит-экономика и эффект масштаба, но критична зависимость от качества скоринга, ликвидности залогов и регулирования. При объёмах от 1 млрд/мес — привлекательный актив.
B8: 5 ФАКТОРОВ ПРОВАЛА
B9: 1. Рост дефолтов и медленное взыскание залога → отток инвесторов.
B10: 2. Регуляторные ограничения ЦБ РФ на P2P/краудлендинг и статус платформы.
B11: 3. Недостаток инвесторов (одна сторона маркетплейса) → простой капитала.
B12: 4. Мошенничество с залогами / ошибки оценки → прямые потери и репутация.
B13: 5. Высокий CAC обеих сторон → невыход на точку безубыточности.
... B21: Чтобы основатель (100% доли) получал 3 млн ₽/мес после налогов и дивидендного НДФЛ (13%):
B22: Требуемые дивиденды (до НДФЛ)/мес | C22: =3000000/(1-Допущения!B34)
B23: Требуемая чистая прибыль компании/год | C23: =C22*12
B24: Требуемая EBITDA/год (÷0.75) | C24: =C23/(1-Допущения!B33)
B25: ≈ Необходимый объём финансирования/мес | C25: =(C24/12+Допущения!B30)/Допущения!B23
B26: Вывод: ориентир ≈ 150 млн ₽/мес (~60 сделок). Чистая прибыль компании ~3,5 млн ₽/мес → после НДФЛ 13% даёт основателю ~3 млн ₽/мес. На бОльших объёмах — кратный запас.

Sheet Цель 80 млн
A1: ЦЕЛЬ: +1 МЛН ₽ ЧИСТОЙ ПРИБЫЛИ ПРИ ОБЪЁМЕ 80 МЛН/МЕС
A2: Три варианта достижения цели. Синие ячейки — вводные.
A4: Параметр | B4: Текущая модель | C4: Вар.1 Комиссии | D4: Вар.2 Эконом | E4: Вар.3 Баланс ✓
A5: Объём финансирования/мес | B5: 80000000 | C5: 80000000 | D5: 80000000 | E5: 80000000
A6: — take rate (комиссии всего) | B6: 0.055 | C6: 0.075 | D6: 0.055 | E6: 0.065
A7: — переменные (% объёма) | B7: 0.0202 | C7: 0.0202 | D7: 0.0202 | E7: 0.0172
A8: Постоянные расходы/мес | B8: 3000000 | C8: 3000000 | D8: 1400000 | E8: 2400000
A10: Выручка | B10: =B5*B6 | C10: =C5*C6 | D10: =D5*D6 | E10: =E5*E6
A11: Переменные расходы | B11: =-B5*B7 | C11: =-C5*C7 | D11: =-D5*D7 | E11: =-E5*E7
A12: Маржа вклада | B12: =B10+B11 | C12: =C10+C11 | D12: =D10+D11 | E12: =E10+E11
A13: Постоянные расходы | B13: =-B8 | C13: =-C8 | D13: =-D8 | E13: =-E8
A14: EBITDA | B14: =B12+B13 | C14: =C12+C13 | D14: =D12+D13 | E14: =E12+E13
A15: Амортизация | B15: =-50000 | C15: =-50000 | D15: =-50000 | E15: =-50000
A16: EBIT | B16: =B14+B15 | C16: =C14+C15 | D16: =D14+D15 | E16: =E14+E15
A17: Налог 25% | B17: =-MAX(0,B16)*Допущения!B33 | C17: =-MAX(0,C16)*Допущения!B33 | D17: =-MAX(0,D16)*Допущения!B33 | E17: =-MAX(0,E16)*Допущения!B33
A18: ЧИСТАЯ ПРИБЫЛЬ/мес | B18: =B16+B17 | C18: =C16+C17 | D18: =D16+D17 | E18: =E16+E17
A19: Цель достигнута? (≥1 млн) | B19: =IF(B18>=1000000,"ДА","нет") | C19: =IF(C18>=1000000,"ДА","нет") | D19: =IF(D18>=1000000,"ДА","нет") | E19: =IF(E18>=1000000,"ДА","нет")
A21: Описание вариантов:
A22: Вар.1 «Комиссии»: take rate 5.5%→7.5% (заёмщик 4% + инвестор 2% + допуслуги 1.5%), команда без изменений.
A23: Вар.2 «Эконом»: комиссии как есть, но постоянные урезаны до 1.4 млн (MVP-команда ~5 чел, минимум офиса).
A24: Вар.3 «Баланс» ✓ (рекомендую): take rate 6.5% (заёмщик 3.5%+инвестор 1.5%+допуслуги 1.5%), маркетинг через рефералов 1%→0.7%, команда чуть компактнее (2.4 млн).

Sheet White-label
A1: СЦЕНАРИЙ: РАБОТА ПОД ЧУЖОЙ ЛИЦЕНЗИЕЙ (WHITE-LABEL)
A2: Партнёр с лицензией ЦБ берёт долю выручки. Синяя ячейка — вводная. Расходы оставлены как в базе (комплаенс партнёра — upside).
A3: Доля партнёра (% от выручки) | B3: 0.25
A5: Показатель / Объём в мес | B5: ='Прогноз по объёмам'!B3 | C5: ='Прогноз по объёмам'!C3 | D5: ='Прогноз по объёмам'!D3 | E5: ='Прогноз по объёмам'!E3 | F5: ='Прогноз по объёмам'!F3 | G5: ='Прогноз по объёмам'!G3
A6: Объём финансирования (₽) | B6: ='Прогноз по объёмам'!B4 | C6: ='Прогноз по объёмам'!C4 | D6: ='Прогноз по объёмам'!D4 | E6: ='Прогноз по объёмам'!E4 | F6: ='Прогноз по объёмам'!F4 | G6: ='Прогноз по объёмам'!G4
A7: Выручка валовая (Revenue) | B7: ='Прогноз по объёмам'!B6 | C7: ='Прогноз по объёмам'!C6 | D7: ='Прогноз по объёмам'!D6 | E7: ='Прогноз по объёмам'!E6 | F7: ='Прогноз по объёмам'!F6 | G7: ='Прогноз по объёмам'!G6
A8: − Доля партнёра | B8: =-'Прогноз по объёмам'!B6*$B$3 | C8: =-'Прогноз по объёмам'!C6*$B$3 | D8: =-'Прогноз по объёмам'!D6*$B$3 | E8: =-'Прогноз по объёмам'!E6*$B$3 | F8: =-'Прогноз по объёмам'!F6*$B$3 | G8: =-'Прогноз по объёмам'!G6*$B$3
A9: Выручка платформы (нетто) | B9: ='Прогноз по объёмам'!B6*(1-$B$3) | C9: ='Прогноз по объёмам'!C6*(1-$B$3) | D9: ='Прогноз по объёмам'!D6*(1-$B$3) | E9: ='Прогноз по объёмам'!E6*(1-$B$3) | F9: ='Прогноз по объёмам'!F6*(1-$B$3) | G9: ='Прогноз по объёмам'!G6*(1-$B$3)
A10: − Переменные расходы | B10: ='Прогноз по объёмам'!B7 | C10: ='Прогноз по объёмам'!C7 | D10: ='Прогноз по объёмам'!D7 | E10: ='Прогноз по объёмам'!E7 | F10: ='Прогноз по объёмам'!F7 | G10: ='Прогноз по объёмам'!G7
A11: Маржа вклада | B11: =B9+B10 | C11: =C9+C10 | D11: =D9+D10 | E11: =E9+E10 | F11: =F9+F10 | G11: =G9+G10
A12: − Постоянные расходы | B12: ='Прогноз по объёмам'!B9 | C12: ='Прогноз по объёмам'!C9 | D12: ='Прогноз по объёмам'!D9 | E12: ='Прогноз по объёмам'!E9 | F12: ='Прогноз по объёмам'!F9 | G12: ='Прогноз по объёмам'!G9
A13: EBITDA | B13: =B11+B12 | C13: =C11+C12 | D13: =D11+D12 | E13: =E11+E12 | F13: =F11+F12 | G13: =G11+G12
A14: EBITDA-маржа (к нетто) | B14: =B13/B9 | C14: =C13/C9 | D14: =D13/D9 | E14: =E13/E9 | F14: =F13/F9 | G14: =G13/G9
A15: − Налог на прибыль (25%) | B15: =-MAX(0,B13)*'Допущения'!$B$33 | C15: =-MAX(0,C13)*'Допущения'!$B$33 | D15: =-MAX(0,D13)*'Допущения'!$B$33 | E15: =-MAX(0,E13)*'Допущения'!$B$33 | F15: =-MAX(0,F13)*'Допущения'!$B$33 | G15: =-MAX(0,G13)*'Допущения'!$B$33
A16: ЧИСТАЯ ПРИБЫЛЬ (мес) | B16: =B13+B15 | C16: =C13+C15 | D16: =D13+D15 | E16: =E13+E15 | F16: =F13+F15 | G16: =G13+G15
A17: Чистая прибыль (год) | B17: =B16*12 | C17: =C16*12 | D17: =D16*12 | E17: =E16*12 | F17: =F16*12 | G17: =G16*12
A19: Сравнение EBITDA:
A20: EBITDA — своя лицензия | B20: ='Прогноз по объёмам'!B10 | C20: ='Прогноз по объёмам'!C10 | D20: ='Прогноз по объёмам'!D10 | E20: ='Прогноз по объёмам'!E10 | F20: ='Прогноз по объёмам'!F10 | G20: ='Прогноз по объёмам'!G10
A21: EBITDA — white-label | B21: =B13 | C21: =C13 | D21: =D13 | E21: =E13 | F21: =F13 | G21: =G13
A22: Разница (цена лицензии партнёра) | B22: =B21-B20 | C22: =C21-C20 | D22: =D21-D20 | E22: =E21-E20 | F22: =F21-F20 | G22: =G21-G20
A24: ИТОГ: своя лицензия vs white-label
A25: Take rate — своя | B25: ='Допущения'!B15
A26: Take rate — white-label (нетто) | B26: ='Допущения'!B15*(1-B3)
A27: Маржа вклада — своя | B27: ='Допущения'!B23
A28: Маржа вклада — white-label | B28: ='Допущения'!B15*(1-B3)-'Допущения'!B22
A29: Точка безубыточности — своя (₽/мес) | B29: ='Точка безубыточности'!B7
A30: Точка безубыточности — white-label | B30: ='Допущения'!B30/B28
A31: Рост точки безубыточности | B31: =B30/B29-1
A33: ЧУВСТВИТЕЛЬНОСТЬ К ДОЛЕ ПАРТНЁРА
A34: Доля партнёра | B34: Take rate нетто | C34: Маржа вклада | D34: Точка ББ (₽/мес) | E34: EBITDA @1 млрд
A35: 0.15 | B35: =Допущения!B15*(1-A35) | C35: =Допущения!B15*(1-A35)-Допущения!B22 | D35: =Допущения!B30/C35 | E35: ='Прогноз по объёмам'!E6*(1-A35)+'Прогноз по объёмам'!E7+'Прогноз по объёмам'!E9
A36: 0.25 | B36: =Допущения!B15*(1-A36) | C36: =Допущения!B15*(1-A36)-Допущения!B22 | D36: =Допущения!B30/C36 | E36: ='Прогноз по объёмам'!E6*(1-A36)+'Прогноз по объёмам'!E7+'Прогноз по объёмам'!E9
A37: 0.35 | B37: =Допущения!B15*(1-A37) | C37: =Допущения!B15*(1-A37)-Допущения!B22 | D37: =Допущения!B30/C37 | E37: ='Прогноз по объёмам'!E6*(1-A37)+'Прогноз по объёмам'!E7+'Прогноз по объёмам'!E9

Sheet Сравнение моделей
A1: СРАВНЕНИЕ ТРЁХ МОДЕЛЕЙ ЗАПУСКА
A2: Финансовые строки — формулы (из листов модели). Качественные — оценка.
A4: Показатель | B4: Своя лицензия (ФЗ-259) | C4: Информационный сервис | D4: White-label (25%)
A5: Take rate (нетто) | B5: =Допущения!B15 | C5: =Допущения!B15 | D5: ='White-label'!B26
A6: Маржа вклада | B6: =Допущения!B23 | C6: =Допущения!B23 | D6: ='White-label'!B28
A7: Точка безубыточности (₽/мес) | B7: ='Точка безубыточности'!B7 | C7: ='Точка безубыточности'!B7 | D7: ='White-label'!B30
A8: EBITDA при 1 млрд/мес (₽) | B8: ='Прогноз по объёмам'!E10 | C8: ='Прогноз по объёмам'!E10 | D8: ='White-label'!E13
A9: Капитал на старт | B9: 5 млн собств. + юр. | C9: минимальный | D9: минимальный
A10: Легальность / риск | B10: ✅ полная | C10: ⚠️ риск переквалификации | D10: ✅ полная (под партнёром)
A11: Скорость запуска | B11: месяцы | C11: быстро | D11: недели
A12: Маржа платформы | B12: максимум | C12: максимум | D12: делишь с партнёром
A14: Вывод: инфосервис = та же экономика, что своя лицензия, но с регуляторным риском. White-label дороже по марже, но легально и быстро — оптимален для старта.
